LICENSE
README.md
setup.py
gptq_api.egg-info/PKG-INFO
gptq_api.egg-info/SOURCES.txt
gptq_api.egg-info/dependency_links.txt
gptq_api.egg-info/requires.txt
gptq_api.egg-info/top_level.txt
gptqapi/__init__.py
gptqapi/server.py
gptqapi/api/__init__.py
gptqapi/api/app.py
gptqapi/api/protocol.py
gptqapi/chat/__init__.py
gptqapi/chat/stream_chat.py
gptqapi/extras/__init__.py
gptqapi/extras/callbacks.py
gptqapi/extras/constants.py
gptqapi/extras/logging.py
gptqapi/extras/misc.py
gptqapi/extras/ploting.py
gptqapi/extras/save_and_load.py
gptqapi/extras/template.py
gptqapi/extras/patches/__init__.py
gptqapi/extras/patches/llama_patch.py