Metadata-Version: 2.1
Name: gptq-api
Version: 0.0.3
Summary: OpenAI compatible API server for AutoGPTQ model
Author: Robin Syihab
Author-email: robinsyihab@gmail.com
License: MIT
Classifier: Programming Language :: Python :: 3
Classifier: License :: OSI Approved :: MIT License
Classifier: Operating System :: OS Independent
Requires-Python: >=2.7
License-File: LICENSE
